setup.py
byte_api/__init__.py
byte_api/api.py
byte_api/client.py
byte_api/types.py
byte_api.egg-info/PKG-INFO
byte_api.egg-info/SOURCES.txt
byte_api.egg-info/dependency_links.txt
byte_api.egg-info/requires.txt
byte_api.egg-info/top_level.txt